gleu/__init__.py
gleu/accum.py
gleu/aggreg.py
gleu/corpus_main.py
gleu/count.py
gleu/load.py
gleu/main.py
gleu/ngram.py
gleu/result.py
gleu/score.py
gleu/sent_main.py
gleu/util.py
gleu/verbose.py
gleu-1.1.0.dist-info/LICENSE
gleu-1.1.0.dist-info/METADATA
gleu-1.1.0.dist-info/WHEEL
gleu-1.1.0.dist-info/entry_points.txt
gleu-1.1.0.dist-info/top_level.txt
gleu-1.1.0.dist-info/RECORD
