Metadata-Version: 2.1
Name: gleu
Version: 1.1.0
Summary: GLEU: evaluation metric for grammatical error correction
Home-page: https://github.com/shotakoyama/gleu
Author: Shota Koyama
Author-email: koyamashota0@gmail.com
Classifier: Programming Language :: Python :: 3.11
Classifier: License :: OSI Approved :: MIT License
Classifier: Operating System :: OS Independent
License-File: LICENSE
Requires-Dist: numpy
Requires-Dist: prettytable
